iflow_mcp_mcp_ortools-0.1.0.dist-info/licenses/LICENSE
mcp_ortools/__init__.py
mcp_ortools/parser.py
mcp_ortools/server.py
mcp_ortools/solver.py
mcp_ortools/solver_manager.py
iflow_mcp_mcp_ortools-0.1.0.dist-info/METADATA
iflow_mcp_mcp_ortools-0.1.0.dist-info/WHEEL
iflow_mcp_mcp_ortools-0.1.0.dist-info/entry_points.txt
iflow_mcp_mcp_ortools-0.1.0.dist-info/top_level.txt
iflow_mcp_mcp_ortools-0.1.0.dist-info/RECORD
