Metadata-Version: 2.4
Name: iflow-mcp_mcp-ortools
Version: 0.1.0
Summary: MCP Server with Google OR-Tools backend
Author: Jacck
Requires-Python: >=3.9
License-File: LICENSE
Requires-Dist: ortools>=9.4.1874
Requires-Dist: asyncio>=3.4.3
Requires-Dist: aiohttp>=3.8.1
Requires-Dist: pydantic>=1.9.0
Requires-Dist: mcp>=0.1.0
Dynamic: description-content-type
Dynamic: license-file
Dynamic: requires-python
